no_pry_fshangala/__init__.py
no_pry_fshangala/no_pry_mod.py
no_pry_fshangala-1.1.0.dist-info/LICENSE
no_pry_fshangala-1.1.0.dist-info/METADATA
no_pry_fshangala-1.1.0.dist-info/WHEEL
no_pry_fshangala-1.1.0.dist-info/top_level.txt
no_pry_fshangala-1.1.0.dist-info/RECORD
